setup.py
pddprofile/__init__.py
pddprofile/display.py
pddprofile/normalisation.py
pddprofile.egg-info/PKG-INFO
pddprofile.egg-info/SOURCES.txt
pddprofile.egg-info/dependency_links.txt
pddprofile.egg-info/top_level.txt