Metadata-Version: 1.0
Name: pddprofile
Version: 0.1
Summary: Utilities for PDDs and Profiles
Home-page: UNKNOWN
Author: Simon Biggs
Author-email: mail@simonbiggs.net
License: AGPL3+
Platform: UNKNOWN
